<?xml version="1.0" encoding="utf-8" ?>
<dwsync>
<file name="img8.jpg" server="C:/wamp/www/kanan/" local="131732216420000000" remote="131732216420000000" Dst="0" />
<file name="img9.jpg" server="C:/wamp/www/kanan/" local="131732216420000000" remote="131732216420000000" Dst="0" />
<file name="img10.jpg" server="C:/wamp/www/kanan/" local="131732216100000000" remote="131732216100000000" Dst="0" />
<file name="img2.jpg" server="C:/wamp/www/kanan/" local="131732216200000000" remote="131732216200000000" Dst="0" />
<file name="img1.jpg" server="C:/wamp/www/kanan/" local="131732216100000000" remote="131732216100000000" Dst="0" />
<file name="key-icon-10.png" server="C:/wamp/www/kanan/" local="131539074253169170" remote="131539074250000000" Dst="0" />
<file name="img5.jpg" server="C:/wamp/www/kanan/" local="131732216380000000" remote="131732216380000000" Dst="0" />
<file name="img6.jpg" server="C:/wamp/www/kanan/" local="131732216400000000" remote="131732216400000000" Dst="0" />
<file name="img13.jpg" server="C:/wamp/www/kanan/" local="131732216120000000" remote="131732216120000000" Dst="0" />
<file name="img12.jpg" server="C:/wamp/www/kanan/" local="131732216120000000" remote="131732216120000000" Dst="0" />
<file name="img11.jpg" server="C:/wamp/www/kanan/" local="131732216100000000" remote="131732216100000000" Dst="0" />
<file name="img3.jpg" server="C:/wamp/www/kanan/" local="131732216340000000" remote="131732216340000000" Dst="0" />
<file name="img4.jpg" server="C:/wamp/www/kanan/" local="131732216380000000" remote="131732216380000000" Dst="0" />
<file name="img28.jpg" server="C:/wamp/www/kanan/" local="131732216320000000" remote="131732216320000000" Dst="0" />
<file name="img29.jpg" server="C:/wamp/www/kanan/" local="131732216320000000" remote="131732216320000000" Dst="0" />
<file name="img30.jpg" server="C:/wamp/www/kanan/" local="131732216340000000" remote="131732216340000000" Dst="0" />
<file name="img31.jpg" server="C:/wamp/www/kanan/" local="131732216360000000" remote="131732216360000000" Dst="0" />
<file name="img32.jpg" server="C:/wamp/www/kanan/" local="131732216360000000" remote="131732216360000000" Dst="0" />
<file name="com_stock.png" server="C:/wamp/www/kanan/" local="131619917462695773" remote="131619917460000000" Dst="0" />
<file name="Computer-icon.png" server="C:/wamp/www/kanan/" local="131539078909522160" remote="131539078900000000" Dst="0" />
<file name="bacground.jpg" server="C:/wamp/www/kanan/" local="131817502556627793" remote="131817502550000000" Dst="0" />
<file name="logo.png" server="C:/wamp/www/kanan/" local="131817499905643994" remote="131817499900000000" Dst="0" />
<file name="user icon.png" server="C:/wamp/www/kanan/" local="131817503586777838" remote="131817503580000000" Dst="0" />
<file name="computer-ok-icon.png" server="C:/wamp/www/kanan/" local="131817504818516252" remote="131817504810000000" Dst="0" />
<file name="Software-icon.png" server="C:/wamp/www/kanan/" local="131817506771322810" remote="131817506770000000" Dst="0" />
<file name="supplier.png" server="C:/wamp/www/kanan/" local="131817507824243753" remote="131817507820000000" Dst="0" />
<file name="pc-parts-png.png" server="C:/wamp/www/kanan/" local="131817509856375312" remote="131817509850000000" Dst="0" />
<file name="computer_buy.png" server="C:/wamp/www/kanan/" local="131817511063731826" remote="131817511060000000" Dst="0" />
<file name="replace.png" server="C:/wamp/www/kanan/" local="131817516582912701" remote="131817516580000000" Dst="0" />
<file name="repair1.jpg" server="C:/wamp/www/kanan/" local="131817517556742501" remote="131817517550000000" Dst="0" />
<file name="logo.png" server="C:/wamp64/www/kanan/" local="131817499905643994" remote="131817499900000000" Dst="0" />
<file name="img8.jpg" server="C:/wamp64/www/kanan/" local="131732216420000000" remote="131732216420000000" Dst="0" />
<file name="img9.jpg" server="C:/wamp64/www/kanan/" local="131732216420000000" remote="131732216420000000" Dst="0" />
<file name="img10.jpg" server="C:/wamp64/www/kanan/" local="131732216100000000" remote="131732216100000000" Dst="0" />
<file name="img2.jpg" server="C:/wamp64/www/kanan/" local="131732216200000000" remote="131732216200000000" Dst="0" />
<file name="img1.jpg" server="C:/wamp64/www/kanan/" local="131732216100000000" remote="131732216100000000" Dst="0" />
<file name="user icon.png" server="C:/wamp64/www/kanan/" local="131817503586777838" remote="131817503580000000" Dst="0" />
<file name="computer-ok-icon.png" server="C:/wamp64/www/kanan/" local="131817504818516252" remote="131817504810000000" Dst="0" />
<file name="key-icon-10.png" server="C:/wamp64/www/kanan/" local="131539074253169170" remote="131539074250000000" Dst="0" />
<file name="Software-icon.png" server="C:/wamp64/www/kanan/" local="131817506771322810" remote="131817506770000000" Dst="0" />
<file name="supplier.png" server="C:/wamp64/www/kanan/" local="131817507824243753" remote="131817507820000000" Dst="0" />
<file name="img5.jpg" server="C:/wamp64/www/kanan/" local="131732216380000000" remote="131732216380000000" Dst="0" />
<file name="img6.jpg" server="C:/wamp64/www/kanan/" local="131732216400000000" remote="131732216400000000" Dst="0" />
<file name="img13.jpg" server="C:/wamp64/www/kanan/" local="131732216120000000" remote="131732216120000000" Dst="0" />
<file name="img12.jpg" server="C:/wamp64/www/kanan/" local="131732216120000000" remote="131732216120000000" Dst="0" />
<file name="img11.jpg" server="C:/wamp64/www/kanan/" local="131732216100000000" remote="131732216100000000" Dst="0" />
<file name="img3.jpg" server="C:/wamp64/www/kanan/" local="131732216340000000" remote="131732216340000000" Dst="0" />
<file name="img4.jpg" server="C:/wamp64/www/kanan/" local="131732216380000000" remote="131732216380000000" Dst="0" />
<file name="img28.jpg" server="C:/wamp64/www/kanan/" local="131732216320000000" remote="131732216320000000" Dst="0" />
<file name="img29.jpg" server="C:/wamp64/www/kanan/" local="131732216320000000" remote="131732216320000000" Dst="0" />
<file name="img30.jpg" server="C:/wamp64/www/kanan/" local="131732216340000000" remote="131732216340000000" Dst="0" />
<file name="img31.jpg" server="C:/wamp64/www/kanan/" local="131732216360000000" remote="131732216360000000" Dst="0" />
<file name="img32.jpg" server="C:/wamp64/www/kanan/" local="131732216360000000" remote="131732216360000000" Dst="0" />
<file name="bacground.jpg" server="C:/wamp64/www/onlineshopping/" local="131817502556627793" remote="131817502550000000" Dst="0" />
</dwsync>